src/basics.v
module basics (
    input  wire clk,      // clock signal
    input  wire rst_n,    // reset - active low
    input  wire signal_in, // incoming optical pulse
    output reg  detected   // pulse detected output
);

// This runs on every rising clock edge
always @(posedge clk or negedge rst_n) begin
    if (!rst_n) begin
        // reset state
        detected <= 1'b0;
    end else begin
        // normal operation
        detected <= signal_in;
    end
end

endmodule

sim/basics_tb.v
module basics_tb;

// declare signals
reg clk;
reg rst_n;
reg signal_in;
wire detected;

// connect to your module
basics dut (
    .clk(clk),
    .rst_n(rst_n),
    .signal_in(signal_in),
    .detected(detected)
);

// generate clock — toggles every 5ns
always #5 clk = ~clk;

// test sequence
initial begin
    // initialize
    clk = 0;
    rst_n = 0;
    signal_in = 0;

    // apply reset for 20ns
    #20 rst_n = 1;

    // send some pulses
    #10 signal_in = 1;  // pulse HIGH
    #20 signal_in = 0;  // pulse LOW
    #10 signal_in = 1;  // pulse HIGH again
    #15 signal_in = 0;  // pulse LOW

    // wait and finish
    #50 $finish;
end

// print 
initial begin
    $monitor("Time=%0t | rst_n=%b | signal_in=%b | detected=%b",
             $time, rst_n, signal_in, detected);
end

// save waveform file
initial begin
    $dumpfile("basics.vcd");
    $dumpvars(0, basics_tb);
end

endmodule

sim/basics.vcd
$date
	Wed May  6 23:51:46 2026
$end
$version
	Icarus Verilog
$end
$timescale
	1s
$end
$scope module basics_tb $end
$var wire 1 ! detected $end
$var reg 1 " clk $end
$var reg 1 # rst_n $end
$var reg 1 $ signal_in $end
$scope module dut $end
$var wire 1 " clk $end
$var wire 1 # rst_n $end
$var wire 1 $ signal_in $end
$var reg 1 ! detected $end
$upscope $end
$upscope $end
$enddefinitions $end
$comment Show the parameter values. $end
$dumpall
$end
#0
$dumpvars
0$
0#
0"
0!
$end
#5
1"
#10
0"
#15
1"
#20
0"
1#
#25
1"
#30
0"
1$
#35
1!
1"
#40
0"
#45
1"
#50
0"
0$
#55
0!
1"
#60
0"
1$
#65
1!
1"
#70
0"
#75
0!
1"
0$
