src/freq_counter.v
// ============================================
// Frequency Counter
// Counts how many pulses arrive per second
// Author: Rohit Yadav — TU Chemnitz
// Date: May 2026
// ============================================

module freq_counter (
    input  wire        clk,           // system clock
    input  wire        rst_n,         // reset active low
    input  wire        pulse_in,      // optical pulse input
    input  wire [15:0] clk_freq,      // clock frequency in Hz
    output reg  [15:0] pulse_freq,    // measured pulse frequency
    output reg         freq_valid     // high when measurement ready
);

    reg [15:0] pulse_count;   // counts pulses in current window
    reg [15:0] clk_count;     // counts clock cycles in window
    reg        pulse_prev;    // previous pulse state

    always @(posedge clk or negedge rst_n) begin
        if (!rst_n) begin
            pulse_count <= 16'd0;
            clk_count   <= 16'd0;
            pulse_freq  <= 16'd0;
            freq_valid  <= 1'b0;
            pulse_prev  <= 1'b0;
        end else begin
            pulse_prev <= pulse_in;

            // count clock cycles
            clk_count <= clk_count + 1;

            // detect rising edge — count pulses
            if (!pulse_prev && pulse_in) begin
                pulse_count <= pulse_count + 1;
            end

            // when one second has passed
            if (clk_count >= clk_freq - 1) begin
                // save frequency measurement
                pulse_freq  <= pulse_count;
                freq_valid  <= 1'b1;
                // reset for next second
                clk_count   <= 16'd0;
                pulse_count <= 16'd0;
            end else begin
                freq_valid <= 1'b0;
            end
        end
    end

endmodule

sim/freq_counter_tb.v
module freq_counter_tb;

reg         clk;
reg         rst_n;
reg         pulse_in;
reg  [15:0] clk_freq;
wire [15:0] pulse_freq;
wire        freq_valid;

freq_counter dut (
    .clk(clk),
    .rst_n(rst_n),
    .pulse_in(pulse_in),
    .clk_freq(clk_freq),
    .pulse_freq(pulse_freq),
    .freq_valid(freq_valid)
);

// clock — 10ns period
always #5 clk = ~clk;

// task to send one pulse
task send_pulse;
    begin
        pulse_in = 1;
        #20;
        pulse_in = 0;
        #30;
    end
endtask

initial begin
    clk      = 0;
    rst_n    = 0;
    pulse_in = 0;
    clk_freq = 16'd20;

    #20 rst_n = 1;

    // send 5 pulses
    send_pulse;
    send_pulse;
    send_pulse;
    send_pulse;
    send_pulse;

    // wait for measurement window
    #300;

    $finish;
end

initial begin
    $monitor("T=%0t | pulse=%b | freq=%0d | valid=%b",
             $time, pulse_in, pulse_freq, freq_valid);
end

initial begin
    $dumpfile("freq_counter.vcd");
    $dumpvars(0, freq_counter_tb);
end

endmodule

sim/freq_counter.vcd
$date
	Sat May  9 13:35:07 2026
$end
$version
	Icarus Verilog
$end
$timescale
	1s
$end
$scope module freq_counter_tb $end
$var wire 16 ! pulse_freq [15:0] $end
$var wire 1 " freq_valid $end
$var reg 1 # clk $end
$var reg 16 $ clk_freq [15:0] $end
$var reg 1 % pulse_in $end
$var reg 1 & rst_n $end
$scope module dut $end
$var wire 1 # clk $end
$var wire 16 ' clk_freq [15:0] $end
$var wire 1 % pulse_in $end
$var wire 1 & rst_n $end
$var reg 16 ( clk_count [15:0] $end
$var reg 1 " freq_valid $end
$var reg 16 ) pulse_count [15:0] $end
$var reg 16 * pulse_freq [15:0] $end
$var reg 1 + pulse_prev $end
$upscope $end
$scope task send_pulse $end
$upscope $end
$upscope $end
$enddefinitions $end
$comment Show the parameter values. $end
$dumpall
$end
#0
$dumpvars
0+
b0 *
b0 )
b0 (
b10100 '
0&
0%
b10100 $
0#
0"
b0 !
$end
#5
1#
#10
0#
#15
1#
#20
0#
1%
1&
#25
b1 )
b1 (
1+
1#
#30
0#
#35
b10 (
1#
#40
0#
0%
#45
b11 (
0+
1#
#50
0#
#55
b100 (
1#
#60
0#
#65
b101 (
1#
#70
0#
1%
#75
b10 )
b110 (
1+
1#
#80
0#
#85
b111 (
1#
#90
0#
0%
#95
b1000 (
0+
1#
#100
0#
#105
b1001 (
1#
#110
0#
#115
b1010 (
1#
#120
0#
1%
#125
b11 )
b1011 (
1+
1#
#130
0#
#135
b1100 (
1#
#140
0#
0%
#145
b1101 (
0+
1#
#150
0#
#155
b1110 (
1#
#160
0#
#165
b1111 (
1#
#170
0#
1%
#175
b100 )
b10000 (
1+
1#
#180
0#
#185
b10001 (
1#
#190
0#
0%
#195
b10010 (
0+
1#
#200
0#
#205
b10011 (
1#
#210
0#
#215
b0 )
1"
b100 !
b100 *
b0 (
1#
#220
0#
1%
#225
0"
b1 )
b1 (
1+
1#
#230
0#
#235
b10 (
1#
#240
0#
0%
#245
b11 (
0+
1#
#250
0#
#255
b100 (
1#
#260
0#
#265
b101 (
1#
#270
0#
#275
b110 (
1#
#280
0#
#285
b111 (
1#
#290
0#
#295
b1000 (
1#
#300
0#
#305
b1001 (
1#
#310
0#
#315
b1010 (
1#
#320
0#
#325
b1011 (
1#
#330
0#
#335
b1100 (
1#
#340
0#
#345
b1101 (
1#
#350
0#
#355
b1110 (
1#
#360
0#
#365
b1111 (
1#
#370
0#
#375
b10000 (
1#
#380
0#
#385
b10001 (
1#
#390
0#
#395
b10010 (
1#
#400
0#
#405
b10011 (
1#
#410
0#
#415
b0 )
1"
b1 !
b1 *
b0 (
1#
#420
0#
#425
0"
b1 (
1#
#430
0#
#435
b10 (
1#
#440
0#
#445
b11 (
1#
#450
0#
#455
b100 (
1#
#460
0#
#465
b101 (
1#
#470
0#
#475
b110 (
1#
#480
0#
#485
b111 (
1#
#490
0#
#495
b1000 (
1#
#500
0#
#505
b1001 (
1#
#510
0#
#515
b1010 (
1#
#520
0#
#525
b1011 (
1#
#530
0#
#535
b1100 (
1#
#540
0#
#545
b1101 (
1#
#550
0#
#555
b1110 (
1#
#560
0#
#565
b1111 (
1#
