src/pulse_detector.v
// ===========================================
// Photonic Pulse Detector
// Detects rising and falling edges of optical pulses
// ============================================

module pulse_detector (
    input  wire clk,          // system clock
    input  wire rst_n,        // reset active low
    input  wire pulse_in,     // optical pulse input
    output reg  rising_edge,  // high for 1 cycle on rising edge
    output reg  falling_edge, // high for 1 cycle on falling edge
    output reg  pulse_active  // high while pulse is high
);

    // store previous state of pulse
    reg pulse_prev;

    always @(posedge clk or negedge rst_n) begin
        if (!rst_n) begin
            // reset all outputs
            pulse_prev    <= 1'b0;
            rising_edge   <= 1'b0;
            falling_edge  <= 1'b0;
            pulse_active  <= 1'b0;
        end else begin
            // store current state for next cycle
            pulse_prev <= pulse_in;

            // detect rising edge — was 0 now 1
            rising_edge <= (~pulse_prev) & pulse_in;

            // detect falling edge — was 1 now 0
            falling_edge <= pulse_prev & (~pulse_in);

            // pulse is active when input is high
            pulse_active <= pulse_in;
        end
    end

endmodule

sim/pulse_detector_tb.v
module pulse_detector_tb;

reg clk;
reg rst_n;
reg pulse_in;
wire rising_edge;
wire falling_edge;
wire pulse_active;

// connect to module
pulse_detector dut (
    .clk(clk),
    .rst_n(rst_n),
    .pulse_in(pulse_in),
    .rising_edge(rising_edge),
    .falling_edge(falling_edge),
    .pulse_active(pulse_active)
);

// clock generation — 10ns period = 100MHz
always #5 clk = ~clk;

initial begin
    // initialize
    clk      = 0;
    rst_n    = 0;
    pulse_in = 0;

    // release reset
    #20 rst_n = 1;

    // pulse 1 — short pulse
    #10 pulse_in = 1;
    #30 pulse_in = 0;

    // gap between pulses
    #20;

    // pulse 2 — longer pulse
    #10 pulse_in = 1;
    #60 pulse_in = 0;

    // gap
    #20;

    // pulse 3 — very short pulse
    #10 pulse_in = 1;
    #10 pulse_in = 0;

    #50 $finish;
end

initial begin
    $monitor("T=%0t | in=%b | rise=%b | fall=%b | active=%b",
             $time, pulse_in, rising_edge, falling_edge, pulse_active);
end

initial begin
    $dumpfile("pulse_detector.vcd");
    $dumpvars(0, pulse_detector_tb);
end

endmodule

sim/pulse_detector.vcd
$date
	Fri May  8 15:38:36 2026
$end
$version
	Icarus Verilog
$end
$timescale
	1s
$end
$scope module pulse_detector_tb $end
$var wire 1 ! rising_edge $end
$var wire 1 " pulse_active $end
$var wire 1 # falling_edge $end
$var reg 1 $ clk $end
$var reg 1 % pulse_in $end
$var reg 1 & rst_n $end
$scope module dut $end
$var wire 1 $ clk $end
$var wire 1 % pulse_in $end
$var wire 1 & rst_n $end
$var reg 1 # falling_edge $end
$var reg 1 " pulse_active $end
$var reg 1 ' pulse_prev $end
$var reg 1 ! rising_edge $end
$upscope $end
$upscope $end
$enddefinitions $end
$comment Show the parameter values. $end
$dumpall
$end
#0
$dumpvars
0'
0&
0%
0$
0#
0"
0!
$end
#5
1$
#10
0$
#15
1$
#20
0$
1&
#25
1$
#30
0$
1%
#35
1"
1!
1'
1$
#40
0$
#45
0!
1$
#50
0$
#55
1$
#60
0$
0%
#65
0"
1#
0'
1$
#70
0$
#75
0#
1$
#80
0$
#85
1$
#90
0$
1%
#95
1"
1!
1'
1$
#100
0$
#105
0!
1$
#110
0$
#115
1$
#120
0$
#125
1$
#130
0$
#135
1$
#140
0$
#145
1$
#150
0$
0%
#155
0"
1#
0'
1$
#160
0$
#165
0#
1$
#170
0$
#175
1$
#180
0$
1%
#185
1"
1!
1'
1$
#190
0$
0%
#195
0"
1#
0!
0'
1$
#200
0$
#205
0#
1$
