src/pulse_width_counter.v
// ============================================
// Pulse Width Counter
// Measures width of optical pulse in clock cycles
// Author: Rohit Yadav — TU Chemnitz
// Date: May 8 2026
// ============================================

module pulse_width_counter (
    input  wire        clk,          // system clock
    input  wire        rst_n,        // reset active low
    input  wire        pulse_in,     // optical pulse input
    output reg  [15:0] pulse_width,  // measured width in cycles
    output reg         width_valid   // high when measurement ready
);

    reg [15:0] counter;      // counts clock cycles
    reg        pulse_prev;   // previous pulse state

    always @(posedge clk or negedge rst_n) begin
        if (!rst_n) begin
            counter     <= 16'd0;
            pulse_width <= 16'd0;
            width_valid <= 1'b0;
            pulse_prev  <= 1'b0;
        end else begin
            pulse_prev <= pulse_in;

            if (pulse_in) begin
                // pulse is active — count cycles
                counter     <= counter + 1;
                width_valid <= 1'b0;
            end else if (pulse_prev && !pulse_in) begin
                // falling edge — pulse just ended
                // save the width and signal valid
                pulse_width <= counter;
                width_valid <= 1'b1;
                counter     <= 16'd0;
            end else begin
                // no pulse — clear valid after 1 cycle
                width_valid <= 1'b0;
            end
        end
    end

endmodule

sim/pulse_width_counter_tb.v
module pulse_width_counter_tb;

reg         clk;
reg         rst_n;
reg         pulse_in;
wire [15:0] pulse_width;
wire        width_valid;

pulse_width_counter dut (
    .clk(clk),
    .rst_n(rst_n),
    .pulse_in(pulse_in),
    .pulse_width(pulse_width),
    .width_valid(width_valid)
);

always #5 clk = ~clk;

initial begin
    clk      = 0;
    rst_n    = 0;
    pulse_in = 0;

    #20 rst_n = 1;

    // pulse 1 — 10 cycles wide
    #10 pulse_in = 1;
    #100 pulse_in = 0;

    #30;

    // pulse 2 — 5 cycles wide
    #10 pulse_in = 1;
    #50 pulse_in = 0;

    #30;

    // pulse 3 — 20 cycles wide
    #10 pulse_in = 1;
    #200 pulse_in = 0;

    #50 $finish;
end

initial begin
    $monitor("T=%0t | pulse=%b | width=%0d | valid=%b",
             $time, pulse_in, pulse_width, width_valid);
end

initial begin
    $dumpfile("pulse_width.vcd");
    $dumpvars(0, pulse_width_counter_tb);
end

endmodule

sim/pulse_width.vcd
$date
	Fri May  8 16:26:53 2026
$end
$version
	Icarus Verilog
$end
$timescale
	1s
$end
$scope module pulse_width_counter_tb $end
$var wire 1 ! width_valid $end
$var wire 16 " pulse_width [15:0] $end
$var reg 1 # clk $end
$var reg 1 $ pulse_in $end
$var reg 1 % rst_n $end
$scope module dut $end
$var wire 1 # clk $end
$var wire 1 $ pulse_in $end
$var wire 1 % rst_n $end
$var reg 16 & counter [15:0] $end
$var reg 1 ' pulse_prev $end
$var reg 16 ( pulse_width [15:0] $end
$var reg 1 ! width_valid $end
$upscope $end
$upscope $end
$enddefinitions $end
$comment Show the parameter values. $end
$dumpall
$end
#0
$dumpvars
b0 (
0'
b0 &
0%
0$
0#
b0 "
0!
$end
#5
1#
#10
0#
#15
1#
#20
0#
1%
#25
1#
#30
0#
1$
#35
b1 &
1'
1#
#40
0#
#45
b10 &
1#
#50
0#
#55
b11 &
1#
#60
0#
#65
b100 &
1#
#70
0#
#75
b101 &
1#
#80
0#
#85
b110 &
1#
#90
0#
#95
b111 &
1#
#100
0#
#105
b1000 &
1#
#110
0#
#115
b1001 &
1#
#120
0#
#125
b1010 &
1#
#130
0#
0$
#135
b0 &
1!
b1010 "
b1010 (
0'
1#
#140
0#
#145
0!
1#
#150
0#
#155
1#
#160
0#
#165
1#
#170
0#
1$
#175
b1 &
1'
1#
#180
0#
#185
b10 &
1#
#190
0#
#195
b11 &
1#
#200
0#
#205
b100 &
1#
#210
0#
#215
b101 &
1#
#220
0#
0$
#225
b0 &
1!
b101 "
b101 (
0'
1#
#230
0#
#235
0!
1#
#240
0#
#245
1#
#250
0#
#255
1#
#260
0#
1$
#265
b1 &
1'
1#
#270
0#
#275
b10 &
1#
#280
0#
#285
b11 &
1#
#290
0#
#295
b100 &
1#
#300
0#
#305
b101 &
1#
#310
0#
#315
b110 &
1#
#320
0#
#325
b111 &
1#
#330
0#
#335
b1000 &
1#
#340
0#
#345
b1001 &
1#
#350
0#
#355
b1010 &
1#
#360
0#
#365
b1011 &
1#
#370
0#
#375
b1100 &
1#
#380
0#
#385
b1101 &
1#
#390
0#
#395
b1110 &
1#
#400
0#
#405
b1111 &
1#
#410
0#
#415
b10000 &
1#
#420
0#
#425
b10001 &
1#
#430
0#
#435
b10010 &
1#
#440
0#
#445
b10011 &
1#
#450
0#
#455
b10100 &
1#
#460
0#
0$
#465
b0 &
1!
b10100 "
b10100 (
0'
1#
#470
0#
#475
0!
1#
