src/uart_tx.v
// ============================================
// UART Transmitter
// Sends pulse data to laptop at 9600 baud
// Author: Rohit Yadav
// ============================================

module uart_tx (
    input  wire        clk,        // system clock
    input  wire        rst_n,      // reset active low
    input  wire        send,       // trigger to send data
    input  wire [7:0]  data,       // 8-bit data to send
    output reg         tx,         // UART transmit pin
    output reg         busy        // high while transmitting
);

    // UART parameters
    // For 100MHz clock, 9600 baud:
    // clk_per_bit = 100MHz / 9600 = 10416
    // For simulation we use smaller value
    parameter CLK_PER_BIT = 16'd10;

    // state machine states
    parameter IDLE  = 2'd0;
    parameter START = 2'd1;
    parameter DATA  = 2'd2;
    parameter STOP  = 2'd3;

    reg [1:0]  state;
    reg [15:0] clk_count;
    reg [2:0]  bit_index;
    reg [7:0]  data_reg;

    always @(posedge clk or negedge rst_n) begin
        if (!rst_n) begin
            state     <= IDLE;
            tx        <= 1'b1;  // UART idle = HIGH
            busy      <= 1'b0;
            clk_count <= 16'd0;
            bit_index <= 3'd0;
            data_reg  <= 8'd0;
        end else begin
            case (state)

                IDLE: begin
                    tx   <= 1'b1;  // keep line HIGH
                    busy <= 1'b0;
                    if (send) begin
                        // start transmission
                        data_reg  <= data;
                        state     <= START;
                        busy      <= 1'b1;
                        clk_count <= 16'd0;
                    end
                end

                START: begin
                    tx <= 1'b0;  // start bit = LOW
                    if (clk_count < CLK_PER_BIT - 1) begin
                        clk_count <= clk_count + 1;
                    end else begin
                        clk_count <= 16'd0;
                        bit_index <= 3'd0;
                        state     <= DATA;
                    end
                end

                DATA: begin
                    tx <= data_reg[bit_index];  // send each bit
                    if (clk_count < CLK_PER_BIT - 1) begin
                        clk_count <= clk_count + 1;
                    end else begin
                        clk_count <= 16'd0;
                        if (bit_index < 7) begin
                            bit_index <= bit_index + 1;
                        end else begin
                            state <= STOP;
                        end
                    end
                end

                STOP: begin
                    tx <= 1'b1;  // stop bit = HIGH
                    if (clk_count < CLK_PER_BIT - 1) begin
                        clk_count <= clk_count + 1;
                    end else begin
                        clk_count <= 16'd0;
                        state     <= IDLE;
                        busy      <= 1'b0;
                    end
                end

            endcase
        end
    end

endmodule

src/freq_counter.v
// ============================================
// Frequency Counter
// Counts how many pulses arrive per second
// Author: Rohit Yadav — TU Chemnitz
// Date: May 2026
// ============================================

module freq_counter (
    input  wire        clk,           // system clock
    input  wire        rst_n,         // reset active low
    input  wire        pulse_in,      // optical pulse input
    input  wire [15:0] clk_freq,      // clock frequency in Hz
    output reg  [15:0] pulse_freq,    // measured pulse frequency
    output reg         freq_valid     // high when measurement ready
);

    reg [15:0] pulse_count;   // counts pulses in current window
    reg [15:0] clk_count;     // counts clock cycles in window
    reg        pulse_prev;    // previous pulse state

    always @(posedge clk or negedge rst_n) begin
        if (!rst_n) begin
            pulse_count <= 16'd0;
            clk_count   <= 16'd0;
            pulse_freq  <= 16'd0;
            freq_valid  <= 1'b0;
            pulse_prev  <= 1'b0;
        end else begin
            pulse_prev <= pulse_in;

            // count clock cycles
            clk_count <= clk_count + 1;

            // detect rising edge — count pulses
            if (!pulse_prev && pulse_in) begin
                pulse_count <= pulse_count + 1;
            end

            // when one second has passed
            if (clk_count >= clk_freq - 1) begin
                // save frequency measurement
                pulse_freq  <= pulse_count;
                freq_valid  <= 1'b1;
                // reset for next second
                clk_count   <= 16'd0;
                pulse_count <= 16'd0;
            end else begin
                freq_valid <= 1'b0;
            end
        end
    end

endmodule

src/pulse_width_counter.v
// ============================================
// Pulse Width Counter
// Measures width of optical pulse in clock cycles
// Author: Rohit Yadav — TU Chemnitz
// Date: May 8 2026
// ============================================

module pulse_width_counter (
    input  wire        clk,          // system clock
    input  wire        rst_n,        // reset active low
    input  wire        pulse_in,     // optical pulse input
    output reg  [15:0] pulse_width,  // measured width in cycles
    output reg         width_valid   // high when measurement ready
);

    reg [15:0] counter;      // counts clock cycles
    reg        pulse_prev;   // previous pulse state

    always @(posedge clk or negedge rst_n) begin
        if (!rst_n) begin
            counter     <= 16'd0;
            pulse_width <= 16'd0;
            width_valid <= 1'b0;
            pulse_prev  <= 1'b0;
        end else begin
            pulse_prev <= pulse_in;

            if (pulse_in) begin
                // pulse is active — count cycles
                counter     <= counter + 1;
                width_valid <= 1'b0;
            end else if (pulse_prev && !pulse_in) begin
                // falling edge — pulse just ended
                // save the width and signal valid
                pulse_width <= counter;
                width_valid <= 1'b1;
                counter     <= 16'd0;
            end else begin
                // no pulse — clear valid after 1 cycle
                width_valid <= 1'b0;
            end
        end
    end

endmodule

src/pulse_detector.v
// ===========================================
// Photonic Pulse Detector
// Detects rising and falling edges of optical pulses
// ============================================

module pulse_detector (
    input  wire clk,          // system clock
    input  wire rst_n,        // reset active low
    input  wire pulse_in,     // optical pulse input
    output reg  rising_edge,  // high for 1 cycle on rising edge
    output reg  falling_edge, // high for 1 cycle on falling edge
    output reg  pulse_active  // high while pulse is high
);

    // store previous state of pulse
    reg pulse_prev;

    always @(posedge clk or negedge rst_n) begin
        if (!rst_n) begin
            // reset all outputs
            pulse_prev    <= 1'b0;
            rising_edge   <= 1'b0;
            falling_edge  <= 1'b0;
            pulse_active  <= 1'b0;
        end else begin
            // store current state for next cycle
            pulse_prev <= pulse_in;

            // detect rising edge — was 0 now 1
            rising_edge <= (~pulse_prev) & pulse_in;

            // detect falling edge — was 1 now 0
            falling_edge <= pulse_prev & (~pulse_in);

            // pulse is active when input is high
            pulse_active <= pulse_in;
        end
    end

endmodule

src/top.v
// ============================================
// Photonic Pulse Detector — Top Module
// Connects all 4 modules
// Author: Rohit Yadav 
// ============================================

module top (
    input  wire clk,        // system clock
    input  wire rst_n,      // reset active low
    input  wire pulse_in,   // optical pulse input
    output wire tx,         // UART output to laptop
    output wire busy        // UART busy flag
);

    // internal wires connecting modules
    wire        rising_edge;
    wire        falling_edge;
    wire        pulse_active;
    wire [15:0] pulse_width;
    wire        width_valid;
    wire [15:0] pulse_freq;
    wire        freq_valid;
    wire        send;
    wire [7:0]  tx_data;

    // clock frequency — 100MHz for real chip
    wire [15:0] clk_freq = 16'd100;

    // Module 1 — Pulse Detector
    pulse_detector m1 (
        .clk(clk),
        .rst_n(rst_n),
        .pulse_in(pulse_in),
        .rising_edge(rising_edge),
        .falling_edge(falling_edge),
        .pulse_active(pulse_active)
    );

    // Module 2 — Pulse Width Counter
    pulse_width_counter m2 (
        .clk(clk),
        .rst_n(rst_n),
        .pulse_in(pulse_in),
        .pulse_width(pulse_width),
        .width_valid(width_valid)
    );

    // Module 3 — Frequency Counter
    freq_counter m3 (
        .clk(clk),
        .rst_n(rst_n),
        .pulse_in(pulse_in),
        .clk_freq(clk_freq),
        .pulse_freq(pulse_freq),
        .freq_valid(freq_valid)
    );

    // data selector — send width first then frequency
    assign send    = width_valid | freq_valid;
    assign tx_data = width_valid ? pulse_width[7:0] : pulse_freq[7:0];

    // Module 4 — UART Transmitter
    uart_tx m4 (
        .clk(clk),
        .rst_n(rst_n),
        .send(send),
        .data(tx_data),
        .tx(tx),
        .busy(busy)
    );

endmodule

sim/top_tb.v
module top_tb;

reg  clk;
reg  rst_n;
reg  pulse_in;
wire tx;
wire busy;

top dut (
    .clk(clk),
    .rst_n(rst_n),
    .pulse_in(pulse_in),
    .tx(tx),
    .busy(busy)
);

always #5 clk = ~clk;

task send_pulse;
    input [15:0] width;
    begin
        pulse_in = 1;
        repeat(width) @(posedge clk);
        pulse_in = 0;
        repeat(10) @(posedge clk);
    end
endtask

initial begin
    clk      = 0;
    rst_n    = 0;
    pulse_in = 0;

    #20 rst_n = 1;

    // send 3 pulses of different widths
    send_pulse(10);
    send_pulse(20);
    send_pulse(5);

    // wait for UART to finish
    #2000;

    $finish;
end

initial begin
    $monitor("T=%0t | pulse=%b | tx=%b | busy=%b",
             $time, pulse_in, tx, busy);
end

initial begin
    $dumpfile("top.vcd");
    $dumpvars(0, top_tb);
end

endmodule

sim/top.vcd
$date
	Sat May  9 13:47:20 2026
$end
$version
	Icarus Verilog
$end
$timescale
	1s
$end
$scope module top_tb $end
$var wire 1 ! tx $end
$var wire 1 " busy $end
$var reg 1 # clk $end
$var reg 1 $ pulse_in $end
$var reg 1 % rst_n $end
$scope module dut $end
$var wire 1 # clk $end
$var wire 16 & clk_freq [15:0] $end
$var wire 1 $ pulse_in $end
$var wire 1 % rst_n $end
$var wire 1 ' send $end
$var wire 1 ( width_valid $end
$var wire 8 ) tx_data [7:0] $end
$var wire 1 ! tx $end
$var wire 1 * rising_edge $end
$var wire 16 + pulse_width [15:0] $end
$var wire 16 , pulse_freq [15:0] $end
$var wire 1 - pulse_active $end
$var wire 1 . freq_valid $end
$var wire 1 / falling_edge $end
$var wire 1 " busy $end
$scope module m1 $end
$var wire 1 # clk $end
$var wire 1 $ pulse_in $end
$var wire 1 % rst_n $end
$var reg 1 / falling_edge $end
$var reg 1 - pulse_active $end
$var reg 1 0 pulse_prev $end
$var reg 1 * rising_edge $end
$upscope $end
$scope module m2 $end
$var wire 1 # clk $end
$var wire 1 $ pulse_in $end
$var wire 1 % rst_n $end
$var reg 16 1 counter [15:0] $end
$var reg 1 2 pulse_prev $end
$var reg 16 3 pulse_width [15:0] $end
$var reg 1 ( width_valid $end
$upscope $end
$scope module m3 $end
$var wire 1 # clk $end
$var wire 16 4 clk_freq [15:0] $end
$var wire 1 $ pulse_in $end
$var wire 1 % rst_n $end
$var reg 16 5 clk_count [15:0] $end
$var reg 1 . freq_valid $end
$var reg 16 6 pulse_count [15:0] $end
$var reg 16 7 pulse_freq [15:0] $end
$var reg 1 8 pulse_prev $end
$upscope $end
$scope module m4 $end
$var wire 1 # clk $end
$var wire 8 9 data [7:0] $end
$var wire 1 % rst_n $end
$var wire 1 ' send $end
$var parameter 16 : CLK_PER_BIT $end
$var parameter 2 ; DATA $end
$var parameter 2 < IDLE $end
$var parameter 2 = START $end
$var parameter 2 > STOP $end
$var reg 3 ? bit_index [2:0] $end
$var reg 1 " busy $end
$var reg 16 @ clk_count [15:0] $end
$var reg 8 A data_reg [7:0] $end
$var reg 2 B state [1:0] $end
$var reg 1 ! tx $end
$upscope $end
$upscope $end
$scope task send_pulse $end
$var reg 16 C width [15:0] $end
$upscope $end
$upscope $end
$enddefinitions $end
$comment Show the parameter values. $end
$dumpall
b11 >
b1 =
b0 <
b10 ;
b1010 :
$end
#0
$dumpvars
bx C
b0 B
b0 A
b0 @
b0 ?
b0 9
08
b0 7
b0 6
b0 5
b1100100 4
b0 3
02
b0 1
00
0/
0.
0-
b0 ,
b0 +
0*
b0 )
0(
0'
b1100100 &
0%
0$
0#
0"
1!
$end
#5
1#
#10
0#
#15
1#
#20
0#
1$
b1010 C
1%
#25
b1 6
b1 5
18
b1 1
12
1-
1*
10
1#
#30
0#
#35
0*
b10 1
b10 5
1#
#40
0#
#45
b11 5
b11 1
1#
#50
0#
#55
b100 1
b100 5
1#
#60
0#
#65
b101 5
b101 1
1#
#70
0#
#75
b110 1
b110 5
1#
#80
0#
#85
b111 5
b111 1
1#
#90
0#
#95
b1000 1
b1000 5
1#
#100
0#
#105
b1001 5
b1001 1
1#
#110
0#
#115
b1001 )
b1001 9
1'
0-
1/
00
b0 1
1(
b1001 +
b1001 3
02
b1010 5
08
0$
1#
#120
0#
#125
b0 )
b0 9
0'
1"
b1 B
b1001 A
b1011 5
0(
0/
1#
#130
0#
#135
b1100 5
b1 @
0!
1#
#140
0#
#145
b10 @
b1101 5
1#
#150
0#
#155
b1110 5
b11 @
1#
#160
0#
#165
b100 @
b1111 5
1#
#170
0#
#175
b10000 5
b101 @
1#
#180
0#
#185
b110 @
b10001 5
1#
#190
0#
#195
b10010 5
b111 @
1#
#200
0#
#205
b1000 @
b10011 5
1#
#210
0#
#215
1-
1*
10
b1 1
12
b10 6
b10100 5
18
b1001 @
1$
b10100 C
1#
#220
0#
#225
b10 B
b0 @
b10101 5
b10 1
0*
1#
#230
0#
#235
b11 1
b10110 5
b1 @
1!
1#
#240
0#
#245
b10 @
b10111 5
b100 1
1#
#250
0#
#255
b101 1
b11000 5
b11 @
1#
#260
0#
#265
b100 @
b11001 5
b110 1
1#
#270
0#
#275
b111 1
b11010 5
b101 @
1#
#280
0#
#285
b110 @
b11011 5
b1000 1
1#
#290
0#
#295
b1001 1
b11100 5
b111 @
1#
#300
0#
#305
b1000 @
b11101 5
b1010 1
1#
#310
0#
#315
b1011 1
b11110 5
b1001 @
1#
#320
0#
#325
b1 ?
b0 @
b11111 5
b1100 1
1#
#330
0#
#335
b1101 1
b100000 5
b1 @
0!
1#
#340
0#
#345
b10 @
b100001 5
b1110 1
1#
#350
0#
#355
b1111 1
b100010 5
b11 @
1#
#360
0#
#365
b100 @
b100011 5
b10000 1
1#
#370
0#
#375
b10001 1
b100100 5
b101 @
1#
#380
0#
#385
b110 @
b100101 5
b10010 1
1#
#390
0#
#395
b10011 1
b100110 5
b111 @
1#
#400
0#
#405
b1000 @
b100111 5
b10100 1
1#
#410
0#
#415
b10100 )
b10100 9
1'
0-
1/
00
b0 1
1(
b10100 +
b10100 3
02
b101000 5
08
b1001 @
0$
1#
#420
0#
#425
b0 )
b0 9
0'
b10 ?
b0 @
b101001 5
0(
0/
1#
#430
0#
#435
b101010 5
b1 @
1#
#440
0#
#445
b10 @
b101011 5
1#
#450
0#
#455
b101100 5
b11 @
1#
#460
0#
#465
b100 @
b101101 5
1#
#470
0#
#475
b101110 5
b101 @
1#
#480
0#
#485
b110 @
b101111 5
1#
#490
0#
#495
b110000 5
b111 @
1#
#500
0#
#505
b1000 @
b110001 5
1#
#510
0#
#515
1-
1*
10
b1 1
12
b11 6
b110010 5
18
b1001 @
1$
b101 C
1#
#520
0#
#525
b11 ?
b0 @
b110011 5
b10 1
0*
1#
#530
0#
#535
b11 1
b110100 5
b1 @
1!
1#
#540
0#
#545
b10 @
b110101 5
b100 1
1#
#550
0#
#555
b101 1
b110110 5
b11 @
1#
#560
0#
#565
b101 )
b101 9
1'
b100 @
b110111 5
08
b0 1
1(
b101 +
b101 3
02
0-
1/
00
0$
1#
#570
0#
#575
b0 )
b0 9
0'
0/
0(
b111000 5
b101 @
1#
#580
0#
#585
b110 @
b111001 5
1#
#590
0#
#595
b111010 5
b111 @
1#
#600
0#
#605
b1000 @
b111011 5
1#
#610
0#
#615
b111100 5
b1001 @
1#
#620
0#
#625
b100 ?
b0 @
b111101 5
1#
#630
0#
#635
b111110 5
b1 @
0!
1#
#640
0#
#645
b10 @
b111111 5
1#
#650
0#
#655
b1000000 5
b11 @
1#
#660
0#
#665
b100 @
b1000001 5
1#
#670
0#
#675
b1000010 5
b101 @
1#
#680
0#
#685
b110 @
b1000011 5
1#
#690
0#
#695
b1000100 5
b111 @
1#
#700
0#
#705
b1000 @
b1000101 5
1#
#710
0#
#715
b1000110 5
b1001 @
1#
#720
0#
#725
b101 ?
b0 @
b1000111 5
1#
#730
0#
#735
b1001000 5
b1 @
1#
#740
0#
#745
b10 @
b1001001 5
1#
#750
0#
#755
b1001010 5
b11 @
1#
#760
0#
#765
b100 @
b1001011 5
1#
#770
0#
#775
b1001100 5
b101 @
1#
#780
0#
#785
b110 @
b1001101 5
1#
#790
0#
#795
b1001110 5
b111 @
1#
#800
0#
#805
b1000 @
b1001111 5
1#
#810
0#
#815
b1010000 5
b1001 @
1#
#820
0#
#825
b110 ?
b0 @
b1010001 5
1#
#830
0#
#835
b1010010 5
b1 @
1#
#840
0#
#845
b10 @
b1010011 5
1#
#850
0#
#855
b1010100 5
b11 @
1#
#860
0#
#865
b100 @
b1010101 5
1#
#870
0#
#875
b1010110 5
b101 @
1#
#880
0#
#885
b110 @
b1010111 5
1#
#890
0#
#895
b1011000 5
b111 @
1#
#900
0#
#905
b1000 @
b1011001 5
1#
#910
0#
#915
b1011010 5
b1001 @
1#
#920
0#
#925
b111 ?
b0 @
b1011011 5
1#
#930
0#
#935
b1011100 5
b1 @
1#
#940
0#
#945
b10 @
b1011101 5
1#
#950
0#
#955
b1011110 5
b11 @
1#
#960
0#
#965
b100 @
b1011111 5
1#
#970
0#
#975
b1100000 5
b101 @
1#
#980
0#
#985
b110 @
b1100001 5
1#
#990
0#
#995
b1100010 5
b111 @
1#
#1000
0#
#1005
b1000 @
b1100011 5
1#
#1010
0#
#1015
b11 )
b11 9
1'
b0 6
1.
b11 ,
b11 7
b0 5
b1001 @
1#
#1020
0#
#1025
0'
b11 B
b0 @
0.
b1 5
1#
#1030
0#
#1035
b10 5
b1 @
1!
1#
#1040
0#
#1045
b10 @
b11 5
1#
#1050
0#
#1055
b100 5
b11 @
1#
#1060
0#
#1065
b100 @
b101 5
1#
#1070
0#
#1075
b110 5
b101 @
1#
#1080
0#
#1085
b110 @
b111 5
1#
#1090
0#
#1095
b1000 5
b111 @
1#
#1100
0#
#1105
b1000 @
b1001 5
1#
#1110
0#
#1115
b1010 5
b1001 @
1#
#1120
0#
#1125
0"
b0 B
b0 @
b1011 5
1#
#1130
0#
#1135
b1100 5
1#
#1140
0#
#1145
b1101 5
1#
#1150
0#
#1155
b1110 5
1#
#1160
0#
#1165
b1111 5
1#
#1170
0#
#1175
b10000 5
1#
#1180
0#
#1185
b10001 5
1#
#1190
0#
#1195
b10010 5
1#
#1200
0#
#1205
b10011 5
1#
#1210
0#
#1215
b10100 5
1#
#1220
0#
#1225
b10101 5
1#
#1230
0#
#1235
b10110 5
1#
#1240
0#
#1245
b10111 5
1#
#1250
0#
#1255
b11000 5
1#
#1260
0#
#1265
b11001 5
1#
#1270
0#
#1275
b11010 5
1#
#1280
0#
#1285
b11011 5
1#
#1290
0#
#1295
b11100 5
1#
#1300
0#
#1305
b11101 5
1#
#1310
0#
#1315
b11110 5
1#
#1320
0#
#1325
b11111 5
1#
#1330
0#
#1335
b100000 5
1#
#1340
0#
#1345
b100001 5
1#
#1350
0#
#1355
b100010 5
1#
#1360
0#
#1365
b100011 5
1#
#1370
0#
#1375
b100100 5
1#
#1380
0#
#1385
b100101 5
1#
#1390
0#
#1395
b100110 5
1#
#1400
0#
#1405
b100111 5
1#
#1410
0#
#1415
b101000 5
1#
#1420
0#
#1425
b101001 5
1#
#1430
0#
#1435
b101010 5
1#
#1440
0#
#1445
b101011 5
1#
#1450
0#
#1455
b101100 5
1#
#1460
0#
#1465
b101101 5
1#
#1470
0#
#1475
b101110 5
1#
#1480
0#
#1485
b101111 5
1#
#1490
0#
#1495
b110000 5
1#
#1500
0#
#1505
b110001 5
1#
#1510
0#
#1515
b110010 5
1#
#1520
0#
#1525
b110011 5
1#
#1530
0#
#1535
b110100 5
1#
#1540
0#
#1545
b110101 5
1#
#1550
0#
#1555
b110110 5
1#
#1560
0#
#1565
b110111 5
1#
#1570
0#
#1575
b111000 5
1#
#1580
0#
#1585
b111001 5
1#
#1590
0#
#1595
b111010 5
1#
#1600
0#
#1605
b111011 5
1#
#1610
0#
#1615
b111100 5
1#
#1620
0#
#1625
b111101 5
1#
#1630
0#
#1635
b111110 5
1#
#1640
0#
#1645
b111111 5
1#
#1650
0#
#1655
b1000000 5
1#
#1660
0#
#1665
b1000001 5
1#
#1670
0#
#1675
b1000010 5
1#
#1680
0#
#1685
b1000011 5
1#
#1690
0#
#1695
b1000100 5
1#
#1700
0#
#1705
b1000101 5
1#
#1710
0#
#1715
b1000110 5
1#
#1720
0#
#1725
b1000111 5
1#
#1730
0#
#1735
b1001000 5
1#
#1740
0#
#1745
b1001001 5
1#
#1750
0#
#1755
b1001010 5
1#
#1760
0#
#1765
b1001011 5
1#
#1770
0#
#1775
b1001100 5
1#
#1780
0#
#1785
b1001101 5
1#
#1790
0#
#1795
b1001110 5
1#
#1800
0#
#1805
b1001111 5
1#
#1810
0#
#1815
b1010000 5
1#
#1820
0#
#1825
b1010001 5
1#
#1830
0#
#1835
b1010010 5
1#
#1840
0#
#1845
b1010011 5
1#
#1850
0#
#1855
b1010100 5
1#
#1860
0#
#1865
b1010101 5
1#
#1870
0#
#1875
b1010110 5
1#
#1880
0#
#1885
b1010111 5
1#
#1890
0#
#1895
b1011000 5
1#
#1900
0#
#1905
b1011001 5
1#
#1910
0#
#1915
b1011010 5
1#
#1920
0#
#1925
b1011011 5
1#
#1930
0#
#1935
b1011100 5
1#
#1940
0#
#1945
b1011101 5
1#
#1950
0#
#1955
b1011110 5
1#
#1960
0#
#1965
b1011111 5
1#
#1970
0#
#1975
b1100000 5
1#
#1980
0#
#1985
b1100001 5
1#
#1990
0#
#1995
b1100010 5
1#
#2000
0#
#2005
b1100011 5
1#
#2010
0#
#2015
b0 )
b0 9
1'
1.
b0 ,
b0 7
b0 5
1#
#2020
0#
#2025
0'
1"
b1 B
b0 A
0.
b1 5
1#
#2030
0#
#2035
b10 5
b1 @
0!
1#
#2040
0#
#2045
b10 @
b11 5
1#
#2050
0#
#2055
b100 5
b11 @
1#
#2060
0#
#2065
b100 @
b101 5
1#
#2070
0#
#2075
b110 5
b101 @
1#
#2080
0#
#2085
b110 @
b111 5
1#
#2090
0#
#2095
b1000 5
b111 @
1#
#2100
0#
#2105
b1000 @
b1001 5
1#
#2110
0#
#2115
b1010 5
b1001 @
1#
#2120
0#
#2125
b10 B
b0 ?
b0 @
b1011 5
1#
#2130
0#
#2135
b1100 5
b1 @
1#
#2140
0#
#2145
b10 @
b1101 5
1#
#2150
0#
#2155
b1110 5
b11 @
1#
#2160
0#
#2165
b100 @
b1111 5
1#
#2170
0#
#2175
b10000 5
b101 @
1#
#2180
0#
#2185
b110 @
b10001 5
1#
#2190
0#
#2195
b10010 5
b111 @
1#
#2200
0#
#2205
b1000 @
b10011 5
1#
#2210
0#
#2215
b10100 5
b1001 @
1#
#2220
0#
#2225
b1 ?
b0 @
b10101 5
1#
#2230
0#
#2235
b10110 5
b1 @
1#
#2240
0#
#2245
b10 @
b10111 5
1#
#2250
0#
#2255
b11000 5
b11 @
1#
#2260
0#
#2265
b100 @
b11001 5
1#
#2270
0#
#2275
b11010 5
b101 @
1#
#2280
0#
#2285
b110 @
b11011 5
1#
#2290
0#
#2295
b11100 5
b111 @
1#
#2300
0#
#2305
b1000 @
b11101 5
1#
#2310
0#
#2315
b11110 5
b1001 @
1#
#2320
0#
#2325
b10 ?
b0 @
b11111 5
1#
#2330
0#
#2335
b100000 5
b1 @
1#
#2340
0#
#2345
b10 @
b100001 5
1#
#2350
0#
#2355
b100010 5
b11 @
1#
#2360
0#
#2365
b100 @
b100011 5
1#
#2370
0#
#2375
b100100 5
b101 @
1#
#2380
0#
#2385
b110 @
b100101 5
1#
#2390
0#
#2395
b100110 5
b111 @
1#
#2400
0#
#2405
b1000 @
b100111 5
1#
#2410
0#
#2415
b101000 5
b1001 @
1#
#2420
0#
#2425
b11 ?
b0 @
b101001 5
1#
#2430
0#
#2435
b101010 5
b1 @
1#
#2440
0#
#2445
b10 @
b101011 5
1#
#2450
0#
#2455
b101100 5
b11 @
1#
#2460
0#
#2465
b100 @
b101101 5
1#
#2470
0#
#2475
b101110 5
b101 @
1#
#2480
0#
#2485
b110 @
b101111 5
1#
#2490
0#
#2495
b110000 5
b111 @
1#
#2500
0#
#2505
b1000 @
b110001 5
1#
#2510
0#
#2515
b110010 5
b1001 @
1#
#2520
0#
#2525
b100 ?
b0 @
b110011 5
1#
#2530
0#
#2535
b110100 5
b1 @
1#
#2540
0#
#2545
b10 @
b110101 5
1#
#2550
0#
#2555
b110110 5
b11 @
1#
#2560
0#
#2565
b100 @
b110111 5
1#
#2570
0#
#2575
b111000 5
b101 @
1#
#2580
0#
#2585
b110 @
b111001 5
1#
#2590
0#
#2595
b111010 5
b111 @
1#
#2600
0#
#2605
b1000 @
b111011 5
1#
#2610
0#
#2615
b111100 5
b1001 @
1#
#2620
0#
#2625
b101 ?
b0 @
b111101 5
1#
#2630
0#
#2635
b111110 5
b1 @
1#
#2640
0#
#2645
b10 @
b111111 5
1#
#2650
0#
#2655
b1000000 5
b11 @
1#
#2660
0#
#2665
b100 @
b1000001 5
1#
