src/uart_tx.v
// ============================================
// UART Transmitter
// Sends pulse data to laptop at 9600 baud
// Author: Rohit Yadav
// ============================================

module uart_tx (
    input  wire        clk,        // system clock
    input  wire        rst_n,      // reset active low
    input  wire        send,       // trigger to send data
    input  wire [7:0]  data,       // 8-bit data to send
    output reg         tx,         // UART transmit pin
    output reg         busy        // high while transmitting
);

    // UART parameters
    // For 100MHz clock, 9600 baud:
    // clk_per_bit = 100MHz / 9600 = 10416
    // For simulation we use smaller value
    parameter CLK_PER_BIT = 16'd10;

    // state machine states
    parameter IDLE  = 2'd0;
    parameter START = 2'd1;
    parameter DATA  = 2'd2;
    parameter STOP  = 2'd3;

    reg [1:0]  state;
    reg [15:0] clk_count;
    reg [2:0]  bit_index;
    reg [7:0]  data_reg;

    always @(posedge clk or negedge rst_n) begin
        if (!rst_n) begin
            state     <= IDLE;
            tx        <= 1'b1;  // UART idle = HIGH
            busy      <= 1'b0;
            clk_count <= 16'd0;
            bit_index <= 3'd0;
            data_reg  <= 8'd0;
        end else begin
            case (state)

                IDLE: begin
                    tx   <= 1'b1;  // keep line HIGH
                    busy <= 1'b0;
                    if (send) begin
                        // start transmission
                        data_reg  <= data;
                        state     <= START;
                        busy      <= 1'b1;
                        clk_count <= 16'd0;
                    end
                end

                START: begin
                    tx <= 1'b0;  // start bit = LOW
                    if (clk_count < CLK_PER_BIT - 1) begin
                        clk_count <= clk_count + 1;
                    end else begin
                        clk_count <= 16'd0;
                        bit_index <= 3'd0;
                        state     <= DATA;
                    end
                end

                DATA: begin
                    tx <= data_reg[bit_index];  // send each bit
                    if (clk_count < CLK_PER_BIT - 1) begin
                        clk_count <= clk_count + 1;
                    end else begin
                        clk_count <= 16'd0;
                        if (bit_index < 7) begin
                            bit_index <= bit_index + 1;
                        end else begin
                            state <= STOP;
                        end
                    end
                end

                STOP: begin
                    tx <= 1'b1;  // stop bit = HIGH
                    if (clk_count < CLK_PER_BIT - 1) begin
                        clk_count <= clk_count + 1;
                    end else begin
                        clk_count <= 16'd0;
                        state     <= IDLE;
                        busy      <= 1'b0;
                    end
                end

            endcase
        end
    end

endmodule

sim/uart_tx_tb.v
module uart_tx_tb;

reg        clk;
reg        rst_n;
reg        send;
reg  [7:0] data;
wire       tx;
wire       busy;

uart_tx dut (
    .clk(clk),
    .rst_n(rst_n),
    .send(send),
    .data(data),
    .tx(tx),
    .busy(busy)
);

always #5 clk = ~clk;

initial begin
    clk   = 0;
    rst_n = 0;
    send  = 0;
    data  = 8'd0;

    #20 rst_n = 1;

    // send byte 0x41 = 'A'
    #10 data = 8'h41;
        send = 1;
    #10 send = 0;

    // wait for transmission
    #500;

    // send byte 0x42 = 'B'
    #10 data = 8'h42;
        send = 1;
    #10 send = 0;

    #500 $finish;
end

initial begin
    $monitor("T=%0t | send=%b | data=%h | tx=%b | busy=%b",
             $time, send, data, tx, busy);
end

initial begin
    $dumpfile("uart_tx.vcd");
    $dumpvars(0, uart_tx_tb);
end

endmodule

sim/uart_tx.vcd
$date
	Sat May  9 13:39:21 2026
$end
$version
	Icarus Verilog
$end
$timescale
	1s
$end
$scope module uart_tx_tb $end
$var wire 1 ! tx $end
$var wire 1 " busy $end
$var reg 1 # clk $end
$var reg 8 $ data [7:0] $end
$var reg 1 % rst_n $end
$var reg 1 & send $end
$scope module dut $end
$var wire 1 # clk $end
$var wire 8 ' data [7:0] $end
$var wire 1 % rst_n $end
$var wire 1 & send $end
$var parameter 16 ( CLK_PER_BIT $end
$var parameter 2 ) DATA $end
$var parameter 2 * IDLE $end
$var parameter 2 + START $end
$var parameter 2 , STOP $end
$var reg 3 - bit_index [2:0] $end
$var reg 1 " busy $end
$var reg 16 . clk_count [15:0] $end
$var reg 8 / data_reg [7:0] $end
$var reg 2 0 state [1:0] $end
$var reg 1 ! tx $end
$upscope $end
$upscope $end
$enddefinitions $end
$comment Show the parameter values. $end
$dumpall
b11 ,
b1 +
b0 *
b10 )
b1010 (
$end
#0
$dumpvars
b0 0
b0 /
b0 .
b0 -
b0 '
0&
0%
b0 $
0#
0"
1!
$end
#5
1#
#10
0#
#15
1#
#20
0#
1%
#25
1#
#30
0#
1&
b1000001 $
b1000001 '
#35
1"
b1 0
b1000001 /
1#
#40
0#
0&
#45
b1 .
0!
1#
#50
0#
#55
b10 .
1#
#60
0#
#65
b11 .
1#
#70
0#
#75
b100 .
1#
#80
0#
#85
b101 .
1#
#90
0#
#95
b110 .
1#
#100
0#
#105
b111 .
1#
#110
0#
#115
b1000 .
1#
#120
0#
#125
b1001 .
1#
#130
0#
#135
b10 0
b0 .
1#
#140
0#
#145
b1 .
1!
1#
#150
0#
#155
b10 .
1#
#160
0#
#165
b11 .
1#
#170
0#
#175
b100 .
1#
#180
0#
#185
b101 .
1#
#190
0#
#195
b110 .
1#
#200
0#
#205
b111 .
1#
#210
0#
#215
b1000 .
1#
#220
0#
#225
b1001 .
1#
#230
0#
#235
b1 -
b0 .
1#
#240
0#
#245
b1 .
0!
1#
#250
0#
#255
b10 .
1#
#260
0#
#265
b11 .
1#
#270
0#
#275
b100 .
1#
#280
0#
#285
b101 .
1#
#290
0#
#295
b110 .
1#
#300
0#
#305
b111 .
1#
#310
0#
#315
b1000 .
1#
#320
0#
#325
b1001 .
1#
#330
0#
#335
b10 -
b0 .
1#
#340
0#
#345
b1 .
1#
#350
0#
#355
b10 .
1#
#360
0#
#365
b11 .
1#
#370
0#
#375
b100 .
1#
#380
0#
#385
b101 .
1#
#390
0#
#395
b110 .
1#
#400
0#
#405
b111 .
1#
#410
0#
#415
b1000 .
1#
#420
0#
#425
b1001 .
1#
#430
0#
#435
b11 -
b0 .
1#
#440
0#
#445
b1 .
1#
#450
0#
#455
b10 .
1#
#460
0#
#465
b11 .
1#
#470
0#
#475
b100 .
1#
#480
0#
#485
b101 .
1#
#490
0#
#495
b110 .
1#
#500
0#
#505
b111 .
1#
#510
0#
#515
b1000 .
1#
#520
0#
#525
b1001 .
1#
#530
0#
#535
b100 -
b0 .
1#
#540
0#
#545
b1 .
1#
#550
0#
1&
b1000010 $
b1000010 '
#555
b10 .
1#
#560
0#
0&
#565
b11 .
1#
#570
0#
#575
b100 .
1#
#580
0#
#585
b101 .
1#
#590
0#
#595
b110 .
1#
#600
0#
#605
b111 .
1#
#610
0#
#615
b1000 .
1#
#620
0#
#625
b1001 .
1#
#630
0#
#635
b101 -
b0 .
1#
#640
0#
#645
b1 .
1#
#650
0#
#655
b10 .
1#
#660
0#
#665
b11 .
1#
#670
0#
#675
b100 .
1#
#680
0#
#685
b101 .
1#
#690
0#
#695
b110 .
1#
#700
0#
#705
b111 .
1#
#710
0#
#715
b1000 .
1#
#720
0#
#725
b1001 .
1#
#730
0#
#735
b110 -
b0 .
1#
#740
0#
#745
b1 .
1!
1#
#750
0#
#755
b10 .
1#
#760
0#
#765
b11 .
1#
#770
0#
#775
b100 .
1#
#780
0#
#785
b101 .
1#
#790
0#
#795
b110 .
1#
#800
0#
#805
b111 .
1#
#810
0#
#815
b1000 .
1#
#820
0#
#825
b1001 .
1#
#830
0#
#835
b111 -
b0 .
1#
#840
0#
#845
b1 .
0!
1#
#850
0#
#855
b10 .
1#
#860
0#
#865
b11 .
1#
#870
0#
#875
b100 .
1#
#880
0#
#885
b101 .
1#
#890
0#
#895
b110 .
1#
#900
0#
#905
b111 .
1#
#910
0#
#915
b1000 .
1#
#920
0#
#925
b1001 .
1#
#930
0#
#935
b11 0
b0 .
1#
#940
0#
#945
b1 .
1!
1#
#950
0#
#955
b10 .
1#
#960
0#
#965
b11 .
1#
#970
0#
#975
b100 .
1#
#980
0#
#985
b101 .
1#
#990
0#
#995
b110 .
1#
#1000
0#
#1005
b111 .
1#
#1010
0#
#1015
b1000 .
1#
#1020
0#
#1025
b1001 .
1#
#1030
0#
#1035
0"
b0 0
b0 .
1#
